{"status":0,"data":{"films":[{"id":3590,"name":"拆弹专家","cover":{"origin":"https://pic.maizuo.com/usr/movie/d16085506bf738e6f2763b4d8d5f6cce.jpg"},"poster":{"origin":"https://pic.maizuo.com/usr/movie/3d915dcc28097d3f30a388cdc7099920.jpg","thumbnail":"https://pic.maizuo.com/usr/movie/3d915dcc28097d3f30a388cdc7099920.jpg!150x0"},"intro":"爆炸袭击案 拆弹反恐难","premiereAt":1493308800000,"grade":"8.4","watchCount":192723,"cinemaCount":122,"scheduleCount":1864,"isPromotion":true,"isNowPlaying":true,"isComingSoon":"","isPresold":""},{"id":3631,"name":"喜欢你","cover":{"origin":"https://pic.maizuo.com/usr/movie/88ac8daa5a3941b69b61513193e05bee.jpg"},"poster":{"origin":"https://pic.maizuo.com/usr/movie/66e5b065fb8ecf6d871f447f0697635a.jpg","thumbnail":"https://pic.maizuo.com/usr/movie/66e5b065fb8ecf6d871f447f0697635a.jpg!150x0"},"intro":"爱情换主角 命运中出错","premiereAt":1493222400000,"grade":"8.5","watchCount":105811,"cinemaCount":118,"scheduleCount":1574,"isPromotion":true,"isNowPlaying":true,"isComingSoon":"","isPresold":""},{"id":3609,"name":"春娇救志明","cover":{"origin":"https://pic.maizuo.com/usr/movie/a5da1aa2c03b111215fc9d83cde4987c.jpg"},"poster":{"origin":"https://pic.maizuo.com/usr/movie/99d9cb24c162593f44efd5365f1aff73.jpg","thumbnail":"https://pic.maizuo.com/usr/movie/99d9cb24c162593f44efd5365f1aff73.jpg!150x0"},"intro":"感情趋平淡 唯恐不喜欢","premiereAt":1493308800000,"grade":"7.9","watchCount":251332,"cinemaCount":119,"scheduleCount":1196,"isPromotion":true,"isNowPlaying":true,"isComingSoon":"","isPresold":""},{"id":3364,"name":"记忆大师","cover":{"origin":"https://pic.maizuo.com/usr/movie/ad2e489494445db9eb1b70bf51e9d8de.jpg"},"poster":{"origin":"https://pic.maizuo.com/usr/movie/39f1c6dedf39810780aee8b9b6c1f63a.jpg","thumbnail":"https://pic.maizuo.com/usr/movie/39f1c6dedf39810780aee8b9b6c1f63a.jpg!150x0"},"intro":"记忆可存取 麻烦一大堆","premiereAt":1493308800000,"grade":"8.5","watchCount":136596,"cinemaCount":123,"scheduleCount":2079,"isPromotion":true,"isNowPlaying":true,"isComingSoon":"","isPresold":""},{"id":3456,"name":"速度与激情8","cover":{"origin":"https://pic.maizuo.com/usr/movie/f724ae8171940a23bc75593c1176ebf8.jpg"},"poster":{"origin":"https://pic.maizuo.com/usr/movie/285b69bedff4291808174e940367659f.jpg","thumbnail":"https://pic.maizuo.com/usr/movie/285b69bedff4291808174e940367659f.jpg!150x0"},"intro":"车主要黑化 家族被击垮","premiereAt":1492099200000,"grade":"9.7","watchCount":1764333,"cinemaCount":120,"scheduleCount":1540,"isPromotion":true,"isNowPlaying":true,"isComingSoon":"","isPresold":""}],"page":{"total":8,"current":1}},"msg":"ok"}